permission_rules/__init__.py
permission_rules/admin.py
permission_rules/app_settings.py
permission_rules/apps.py
permission_rules/connect.py
permission_rules/fields.py
permission_rules/migrations/0001_initial.py
permission_rules/migrations/0002_auto_20210729_0731.py
permission_rules/migrations/__init__.py
permission_rules/mixins.py
permission_rules/models.py
permission_rules/permission.py
permission_rules/serializers.py
permission_rules/services/__init__.py
permission_rules/services/permission_rules_file.py
permission_rules/services/permission_rules_getter.py
permission_rules/services/permissions_getter.py
permission_rules/signals.py
permission_rules/urls.py
permission_rules/utils.py
permission_rules/views.py
drf_permission_rules-0.4.6.dist-info/LICENSE
drf_permission_rules-0.4.6.dist-info/METADATA
drf_permission_rules-0.4.6.dist-info/WHEEL
drf_permission_rules-0.4.6.dist-info/RECORD
