Metadata-Version: 2.1
Name: drf-permission-rules
Version: 0.4.6
Summary: Declarative access policies/permissions modeled after AWS' IAM policies.
Home-page: https://github.com/speechki-book/drf-permission-rules
License: MIT
Keywords: django,restframework,policy,authorization,declaritive
Author: Pavel Maltsev
Author-email: pavel@speechki.org
Requires-Python: >=3.9,<4.0
Classifier: License :: OSI Approved :: MIT License
Classifier: Programming Language :: Python :: 3
Classifier: Programming Language :: Python :: 3.9
Classifier: Programming Language :: Python :: 3.10
Classifier: Programming Language :: Python :: 3.11
Classifier: Programming Language :: Python :: 3.12
Classifier: Programming Language :: Python :: 3.13
Requires-Dist: django
Requires-Dist: django-json-widget
Requires-Dist: django-model-utils
Requires-Dist: djangorestframework
Requires-Dist: drf-access-policy
Requires-Dist: drf-yasg[validation]
Requires-Dist: redis
